vtk.py
vtk-9.5.2.dist-info/DELVEWHEEL
vtk-9.5.2.dist-info/LICENSE
vtk-9.5.2.dist-info/METADATA
vtk-9.5.2.dist-info/RECORD
vtk-9.5.2.dist-info/top_level.txt
vtk-9.5.2.dist-info/WHEEL
vtk.libs/.load-order-vtk-9.5.2
vtk.libs/msvcp140-aa2e4bd331e46f2c89293d7086020d3a.dll
vtk.libs/openxr_loader-886112c09bac4191e0d5fb3d640db0f1.dll
vtk.libs/vcruntime140_1-b3b681a9ba92263c8304ea5c2ccbdbb1.dll
vtk.libs/viskoresdiympi_nompi.dll
vtk.libs/viskores_cont-9.5.2.dll
vtk.libs/viskores_filter_clean_grid-9.5.2.dll
vtk.libs/viskores_filter_connected_components-9.5.2.dll
vtk.libs/viskores_filter_contour-9.5.2.dll
vtk.libs/viskores_filter_core-9.5.2.dll
vtk.libs/viskores_filter_density_estimate-9.5.2.dll
vtk.libs/viskores_filter_entity_extraction-9.5.2.dll
vtk.libs/viskores_filter_field_conversion-9.5.2.dll
vtk.libs/viskores_filter_field_transform-9.5.2.dll
vtk.libs/viskores_filter_geometry_refinement-9.5.2.dll
vtk.libs/viskores_filter_mesh_info-9.5.2.dll
vtk.libs/viskores_filter_multi_block-9.5.2.dll
vtk.libs/viskores_filter_resampling-9.5.2.dll
vtk.libs/viskores_filter_vector_analysis-9.5.2.dll
vtk.libs/viskores_worklet-9.5.2.dll
vtk.libs/vtkAcceleratorsVTKmCore-9.5.2.dll
vtk.libs/vtkAcceleratorsVTKmDataModel-9.5.2.dll
vtk.libs/vtkAcceleratorsVTKmFilters-9.5.2.dll
vtk.libs/vtkcgns-9.5.2.dll
vtk.libs/vtkChartsCore-9.5.2.dll
vtk.libs/vtkCommonColor-9.5.2.dll
vtk.libs/vtkCommonComputationalGeometry-9.5.2.dll
vtk.libs/vtkCommonCore-9.5.2.dll
vtk.libs/vtkCommonDataModel-9.5.2.dll
vtk.libs/vtkCommonExecutionModel-9.5.2.dll
vtk.libs/vtkCommonMath-9.5.2.dll
vtk.libs/vtkCommonMisc-9.5.2.dll
vtk.libs/vtkCommonPython-9.5.2.dll
vtk.libs/vtkCommonSystem-9.5.2.dll
vtk.libs/vtkCommonTransforms-9.5.2.dll
vtk.libs/vtkDICOMParser-9.5.2.dll
vtk.libs/vtkDomainsChemistry-9.5.2.dll
vtk.libs/vtkDomainsChemistryOpenGL2-9.5.2.dll
vtk.libs/vtkdoubleconversion-9.5.2.dll
vtk.libs/vtkexodusII-9.5.2.dll
vtk.libs/vtkexpat-9.5.2.dll
vtk.libs/vtkFiltersAMR-9.5.2.dll
vtk.libs/vtkFiltersCellGrid-9.5.2.dll
vtk.libs/vtkFiltersCore-9.5.2.dll
vtk.libs/vtkFiltersExtraction-9.5.2.dll
vtk.libs/vtkFiltersFlowPaths-9.5.2.dll
vtk.libs/vtkFiltersGeneral-9.5.2.dll
vtk.libs/vtkFiltersGeneric-9.5.2.dll
